{"trial_id": "01", "hyperparameters": {"space": [{"class_name": "Int", "config": {"name": "num_layers", "default": null, "conditions": [], "min_value": 1, "max_value": 5, "step": 1, "sampling": "linear"}}, {"class_name": "Int", "config": {"name": "units_0", "default": null, "conditions": [], "min_value": 32, "max_value": 512, "step": 32, "sampling": "linear"}}, {"class_name": "Choice", "config": {"name": "activation", "default": "relu", "conditions": [], "values": ["relu", "tanh"], "ordered": false}}, {"class_name": "Choice", "config": {"name": "learning_rate", "default": 0.1, "conditions": [], "values": [0.1, 0.01, 0.001, 0.0001], "ordered": true}}, {"class_name": "Int", "config": {"name": "units_1", "default": null, "conditions": [], "min_value": 32, "max_value": 512, "step": 32, "sampling": "linear"}}, {"class_name": "Int", "config": {"name": "units_2", "default": null, "conditions": [], "min_value": 32, "max_value": 512, "step": 32, "sampling": "linear"}}, {"class_name": "Int", "config": {"name": "units_3", "default": null, "conditions": [], "min_value": 32, "max_value": 512, "step": 32, "sampling": "linear"}}, {"class_name": "Int", "config": {"name": "units_4", "default": null, "conditions": [], "min_value": 32, "max_value": 512, "step": 32, "sampling": "linear"}}], "values": {"num_layers": 3, "units_0": 320, "activation": "tanh", "learning_rate": 0.0001, "units_1": 192, "units_2": 256, "units_3": 160, "units_4": 416}}, "metrics": {"metrics": {"loss": {"direction": "min", "observations": [{"value": [0.14339123368263246], "step": 189}]}, "accuracy": {"direction": "max", "observations": [{"value": [0.9566961646080017], "step": 189}]}, "val_loss": {"direction": "min", "observations": [{"value": [0.9680057406425476], "step": 189}]}, "val_accuracy": {"direction": "max", "observations": [{"value": [0.6851428747177124], "step": 189}]}}}, "score": 0.6851428747177124, "best_step": 189, "status": "COMPLETED", "message": null}